Workbook

Sheet 1. Summary
A1: MAADEN ARGP - COMMERCIAL RECONCILIATION (all AED, excl WHT/VAT unless stated)
A2: Three internal versions exist. This workbook reconciles them. Prepared 2026-07-06.
B4: Quote Letter (00029, 01 Jun) | C4: Pricing Calculator v2 (00030) | D4: Master Roadmap (00030 v1.0, 02 Jul)
A5: Year 1 build price | B5: ='2. Version Detail'!B10 -> 2841125 | C5: ='2. Version Detail'!C10 -> 9906699 | D5: ='2. Version Detail'!D10 -> 4172335.6
A6: Year 1 manpower plan (FTE-months) | B6: 33 | C6: 83 | D6: 77
A7: Resource cost basis at card rates | B7: ='3. Margin Analysis'!B6 -> 2712600 | C7: ='3. Margin Analysis'!C6 -> 6342600 | D7: ='3. Margin Analysis'!D6 -> 5907000
A8: Implied margin at card rates | B8: ='3. Margin Analysis'!B11 -> -0.097977034 | C8: ='3. Margin Analysis'!C11 -> 0.26373154 | D8: ='3. Margin Analysis'!D11 -> -0.62811688
A9: 5-Year TCO (stated) | B9: 4907333 | D9: 8150000
A10: Timeline | B10: 52 weeks (12 mo) | C10: 12 months | D10: 40 weeks (10 mo)
A11: Payment terms | B11: 20/80/10 (sums to 110% - ERROR) | C11: n/a | D11: 8 tranches = 100%
A13: KEY FINDINGS
A14: 1. Quote letter = 28.7% of its own pricing calculator, uniformly across all 4 phases. No documented discount rationale.
A15: 2. Calculator Phase 4 omits AI/ML Engineer + Security Lead prices (2 roles x 8 mo x 72,600 = 1,161,600 before uplifts). See sheet 2.
A16: 3. Calculator hardware line (15%) misses one resource row in EVERY phase. See sheet 2 corrected column.
A17: 4. Roadmap price (4.6M inc VAT+WHT) cannot cover its own 77 person-month plan at card rates (cost ~5.9M). See sheet 3.
A18: 5. Only the calculator at 9.9M covers its stated manpower with the stated 70% margin - but that is 3.5x the quoted price.
A19: 6. Quote payment terms sum to 110% (20+80+10). Roadmap has a correct 100% 8-tranche schedule - adopt it.
A20: 7. Terminology: calculator applies 5% "VAT", quote applies 5% "WHT". KSA VAT is 15%; cross-border WHT is 5%. Needs tax review (not tax advice - verify with advisor).
A22: DECISION REQUIRED: pick ONE price basis, regenerate quote + roadmap from it, and archive the others.

Sheet 2. Version Detail
A1: YEAR 1 PHASE FEES BY VERSION (AED excl WHT)
A3: Phase | B3: Quote Letter | C3: Calculator v2 (as-is) | D3: Roadmap basis | E3: Calculator CORRECTED | G3: Corrected calc inputs | H3: Resource sum/phase (P4 incl. 2 missing roles)
A4: Phase 1 (W1-4) | B4: 232687.5 | C4: 813730.5 | D4: not phase-split in deck | E4: =G4*(1+$G$12)*(1+$G$13) -> 832243.5 | G4: 425700
A5: Phase 2 (W5-12) | B5: 625685 | C5: 2195193 | E5: =G5*(1+$G$12)*(1+$G$13) -> 2232219 | G5: 1141800
A6: Phase 3 (W13-16) | B6: 269832.5 | C6: 955663.5 | E6: =G6*(1+$G$12)*(1+$G$13) -> 974176.5 | G6: 498300
A7: Phase 4 (W17+) | B7: 1712920 | C7: 5942112 | E7: =G7*(1+$G$12)*(1+$G$13) -> 8361144 | G7: 4276800
A8: Year 1 total | B8: =SUM(B4:B7) -> 2841125 | C8: =SUM(C4:C7) -> 9906699 | D8: 4600000 | E8: =SUM(E4:E7) -> 12399783
A9: Note: Roadmap 4.6M stated as inc VAT+WHT; others excl.
A10: Reference totals (used by Summary) | B10: =B8 -> 2841125 | C10: =C8 -> 9906699 | D10: =B14 -> 4172335.6
A12: Roadmap 4.6M back-calculated to excl-tax basis: | G12: 0.15 | H12: HW+Licences % (per calculator)
A13: less 5% WHT then 5% VAT (as XDH applies them) | G13: 0.7 | H13: Margin % (per calculator)
A14: Net-of-tax roadmap build fee | B14: =4600000/1.05/1.05 -> 4172335.6
A16: CALCULATOR ERRORS FOUND
A17: P4: AI/ML Engineer row - Count 1, Months 8, Price BLANK (formula deleted). Missing 580,800.
A18: P4: KSA Security Lead row - Count 1, Months 8, Price BLANK. Missing 580,800.
A19: All phases: Hardware = 15% x (resource sum MINUS one row). P1 evidence: 52,965 = 15% x (425,700 - 72,600).
A20: Sheet "Year 1 Total" contains an abandoned older rate table (33K/22K/19K roles, all zero) - delete to avoid confusion.
A21: One calculator sheet still dated 2026.03.05.

Sheet 3. Margin Analysis
A1: MARGIN AT CARD RATES vs INTERNAL COST SCENARIOS (AED)
A2: Card rates: PM 99,000/mo; all other roles 72,600/mo (source: calculator Sheet1 rate card, 22 days/mo).
B4: Quote (33 FTE-mo) | C4: Calculator (83 FTE-mo) | D4: Roadmap (77 FTE-mo)
A5: PM months / other months | B5: 12 / 21 | C5: 12 / 71 | D5: 12 / 65
A6: Resource cost at card rates | B6: =12*$B$15+21*$B$16 -> 2712600 | C6: =12*$B$15+71*$B$16 -> 6342600 | D6: =12*$B$15+65*$B$16 -> 5907000
A7: + HW & licences 15% | B7: =B6*1.15 -> 3119490 | C7: =C6*1.15 -> 7293990 | D7: =D6*1.15 -> 6793050
A8: Year 1 price (excl tax) | B8: ='2. Version Detail'!B8 -> 2841125 | C8: ='2. Version Detail'!C8 -> 9906699 | D8: ='2. Version Detail'!B14 -> 4172335.6
A9: Surplus / (shortfall) vs cost+HW | B9: =B8-B7 -> -278365 | C9: =C8-C7 -> 2612709 | D9: =D8-D7 -> -2620714.4
A11: Implied margin % on price | B11: =(B8-B7)/B8 -> -0.097977034 | C11: =(C8-C7)/C8 -> 0.26373154 | D11: =(D8-D7)/D8 -> -0.62811688
A13: ASSUMPTIONS (edit blue cells)
A15: PM rate /mo | B15: 99000
A16: Other role rate /mo | B16: 72600
A17: Internal cost ratio (cost as % of card rate) | B17: 0.6
A19: SENSITIVITY: margin if card rates are SELL and true cost = ratio above
B20: Quote | C20: Calculator | D20: Roadmap
A21: True delivery cost (resources x ratio + HW 15%) | B21: =B6*$B$17*1.15 -> 1871694 | C21: =C6*$B$17*1.15 -> 4376394 | D21: =D6*$B$17*1.15 -> 4075830
A22: Margin % at true cost | B22: =(B8-B21)/B8 -> 0.34121378 | C22: =(C8-C21)/C8 -> 0.55823892 | D22: =(D8-D21)/D8 -> 0.023129875
A24: READ: even at 60% cost ratio, check whether the quote covers the ROADMAP manpower plan - the quote prices the lean 33 FTE-mo plan only.

Sheet 4. Recommendation
A1: RECOMMENDED PATH TO ONE PRICE
A3: 1 | B3: Fix the calculator: restore P4 AI/ML + Security formulas; fix HW range to full resource sum. Corrected total appears in Sheet 2 col E.
A4: 2 | B4: Decide the manpower truth: roadmap 77 person-months is the delivery plan management approved - price against IT, not the 33 FTE-mo lean view.
A5: 3 | B5: Set margin policy explicitly (calculator says 70%, briefing says 35%, roadmap says 40%). One number, documented.
A6: 4 | B6: Regenerate the quote letter from the corrected calculator. Fix payment terms to the roadmap 8-tranche schedule (sums to 100%).
A7: 5 | B7: Get tax treatment verified (5% WHT vs KSA 15% VAT reverse-charge; UAE entity invoicing KSA client). Flag: not tax advice - confirm with advisor.
A8: 6 | B8: Version control: put the final numbers in ONE file; mark superseded files as ARCHIVED in the filename.
