Workbook

Sheet Phase 1
B1: 2026.03.05 XDH-AE-Q26-05-00029
A2: Cost Break Down
A3: SN | B3: Items/ Resources | C3: Remarks | D3: Unit Rate | E3: Count | F3: Months | G3: Price
A4: 1 | B4: Programme Manager | C4: Full Time | D4: 33000 | E4: 1 | F4: 1 | G4: =+SUM(D4*E4*F4) -> 33000
A5: 2 | B5: Solution Architect | C5: Full Time | D5: 22000 | E5: 1 | F5: 1 | G5: =+SUM(D5*E5*F5) -> 22000
A6: 3 | B6: Database Administrator | C6: Full Time | D6: 19000 | E6: 1 | F6: 0.5 | G6: =+SUM(D6*E6*F6) -> 9500
A7: 4 | B7: AI / ML Engineer | C7: Full Time | D7: 19000 | E7: 0 | F7: 0 | G7: =+SUM(D7*E7*F7) -> 0
A8: 5 | B8: KSA Security Lead | C8: Full Time | D8: 19000 | E8: 1 | F8: 1 | G8: =+SUM(D8*E8*F8) -> 19000
A9: 7 | B9: Module Specialist | C9: Full Time | D9: 19000 | E9: 1 | F9: 1 | G9: =+SUM(D9*E9*F9) -> 19000
A10: 8 | B10: Document Controller | C10: Full Time | D10: 19000 | E10: 1 | F10: 1 | G10: =+SUM(D10*E10*F10) -> 19000
A11: 9 | B11: Hardware + Licences | C11: 5% of resources | D11: 0.15 | G11: {=+SUM(G4:G9*D11)} -> 15375
A12: 10 | B12: Margin | D12: 0.7 | G12: =+SUM(G4:G11)*D12 -> 95812.5
A13: 11
A14: 12 | B14: Total (AED) | G14: =SUM(G4:G13) -> 232687.5 | H14: =G14*2 -> 465375
A15: 13 | B15: VAT | G15: =G14*0.05 -> 11634.375 | H15: =G15*2 -> 23268.75
A16: 14 | B16: Total (AED) + VAT | G16: =+SUM(G14)* 1.05 -> 244321.88 | H16: =G16*2 -> 488643.75
A17: 15 | B17: Total (USD) | G17: =+SUM(G14)/3.65 -> 63750

Sheet Phase 2
B1: 2026.03.05 XDH-AE-Q26-05-00029
A2: Cost Break Down
A3: SN | B3: Items/ Resources | C3: Remarks | D3: Unit Rate | E3: Count | F3: Months | G3: Price
A4: 1 | B4: Programme Manager | C4: Full Time | D4: 33000 | E4: 1 | F4: 2 | G4: =+SUM(D4*E4*F4) -> 66000
A5: 2 | B5: Solution Architect | C5: Full Time | D5: 22000 | E5: 2 | F5: 2 | G5: =+SUM(D5*E5*F5) -> 88000
A6: 3 | B6: Database Administrator | C6: Full Time | D6: 19000 | E6: 1 | F6: 2 | G6: =+SUM(D6*E6*F6) -> 38000
A7: 4 | B7: AI / ML Engineer | C7: Full Time | D7: 19000 | E7: 1 | F7: 2 | G7: =+SUM(D7*E7*F7) -> 38000
A8: 5 | B8: KSA Security Lead | C8: Full Time | D8: 19000 | E8: 1 | F8: 1 | G8: =+SUM(D8*E8*F8) -> 19000
A9: 7 | B9: Module Specialist | C9: Full Time | D9: 19000 | E9: 1 | F9: 2 | G9: =+SUM(D9*E9*F9) -> 38000
A10: 8 | B10: Document Controller | C10: Full Time | D10: 19000 | E10: 1 | F10: 2 | G10: =+SUM(D10*E10*F10) -> 38000
A11: 9 | B11: Hardware + Licences | C11: 5% of resources | D11: ='Phase 1'!D11 -> 0.15 | G11: {=+SUM(G4:G9*D11)} -> 43050
A12: 10 | B12: Margin | D12: ='Phase 1'!D12 -> 0.7 | G12: =+SUM(G4:G11)*D12 -> 257635
A13: 11
A14: 12 | B14: Total (AED) | G14: =SUM(G4:G13) -> 625685 | H14: =G14*2 -> 1251370
A15: 13 | B15: VAT | G15: =G14*0.05 -> 31284.25 | H15: =G15*2 -> 62568.5
A16: 14 | B16: Total (AED) + VAT | G16: =+SUM(G14)* 1.05 -> 656969.25 | H16: =G16*2 -> 1313938.5
A17: 15 | B17: Total (USD) | G17: =+SUM(G14)/3.65 -> 171420.55

Sheet Phase 3
B1: 2026.03.05 XDH-AE-Q26-05-00029
A2: Cost Break Down
A3: SN | B3: Items/ Resources | C3: Remarks | D3: Unit Rate | E3: Count | F3: Months | G3: Price
A4: 1 | B4: Programme Manager | C4: Full Time | D4: 33000 | E4: 1 | F4: 1 | G4: =+SUM(D4*E4*F4) -> 33000
A5: 2 | B5: Solution Architect | C5: Full Time | D5: 22000 | E5: 1 | F5: 1 | G5: =+SUM(D5*E5*F5) -> 22000
A6: 3 | B6: Database Administrator | C6: Full Time | D6: 19000 | E6: 1 | F6: 1 | G6: =+SUM(D6*E6*F6) -> 19000
A7: 4 | B7: AI / ML Engineer | C7: Full Time | D7: 19000 | E7: 1 | F7: 1 | G7: =+SUM(D7*E7*F7) -> 19000
A8: 5 | B8: KSA Security Lead | C8: Full Time | D8: 19000 | E8: 1 | F8: 0.5 | G8: =+SUM(D8*E8*F8) -> 9500
A9: 7 | B9: Module Specialist | C9: Full Time | D9: 19000 | E9: 1 | F9: 1 | G9: =+SUM(D9*E9*F9) -> 19000
A10: 8 | B10: Document Controller | C10: Full Time | D10: 19000 | E10: 1 | F10: 1 | G10: =+SUM(D10*E10*F10) -> 19000
A11: 9 | B11: Hardware + Licences | C11: 5% of resources | D11: ='Phase 1'!D11 -> 0.15 | G11: {=+SUM(G4:G9*D11)} -> 18225
A12: 10 | B12: Margin | D12: ='Phase 1'!D12 -> 0.7 | G12: =+SUM(G4:G11)*D12 -> 111107.5
A13: 11
A14: 12 | B14: Total (AED) | G14: =SUM(G4:G13) -> 269832.5 | H14: =G14*2 -> 539665
A15: 13 | B15: VAT | G15: =G14*0.05 -> 13491.625 | H15: =G15*2 -> 26983.25
A16: 14 | B16: Total (AED) + VAT | G16: =+SUM(G14)* 1.05 -> 283324.12 | H16: =G16*2 -> 566648.25
A17: 15 | B17: Total (USD) | G17: =+SUM(G14)/3.65 -> 73926.712

Sheet Phase 4
B1: 2026.03.05 XDH-AE-Q26-05-00029
A2: Cost Break Down
A3: SN | B3: Items/ Resources | C3: Remarks | D3: Unit Rate | E3: Count | F3: Months | G3: Price
A4: 1 | B4: Programme Manager | C4: Full Time | D4: 33000 | E4: 1 | F4: 8 | G4: =+SUM(D4*E4*F4) -> 264000
A5: 2 | B5: Solution Architect | C5: Full Time | D5: 22000 | E5: 1 | F5: 8 | G5: =+SUM(D5*E5*F5) -> 176000
A6: 3 | B6: Database Administrator | C6: Full Time | D6: 19000 | E6: 1 | F6: 8 | G6: =+SUM(D6*E6*F6) -> 152000
A7: 4 | B7: AI / ML Engineer | C7: Full Time | D7: 19000 | E7: 1 | F7: 8
A8: 5 | B8: KSA Security Lead | C8: Full Time | D8: 19000 | E8: 1 | F8: 8
A9: 7 | B9: Module Specialist | C9: Full Time | D9: 19000 | E9: 1 | F9: 8 | G9: =+SUM(D9*E9*F9) -> 152000
A10: 8 | B10: Document Controller | C10: Full Time | D10: 19000 | E10: 1 | F10: 8 | G10: =+SUM(D10*E10*F10) -> 152000
A11: 9 | B11: Hardware + Licences | C11: 5% of resources | D11: ='Phase 1'!D11 -> 0.15 | G11: {=+SUM(G4:G9*D11)} -> 111600
A12: 10 | B12: Margin | D12: ='Phase 1'!D12 -> 0.7 | G12: =+SUM(G4:G11)*D12 -> 705320
A13: 11
A14: 12 | B14: Total (AED) | G14: =SUM(G4:G13) -> 1712920 | H14: =G14*2 -> 3425840
A15: 13 | B15: VAT | G15: =G14*0.05 -> 85646 | H15: =G15*2 -> 171292
A16: 14 | B16: Total (AED) + VAT | G16: =+SUM(G14)* 1.05 -> 1798566 | H16: =G16*2 -> 3597132
A17: 15 | B17: Total (USD) | G17: =+SUM(G14)/3.65 -> 469293.15

Sheet Year 1 Total
B1: 2026.03.05 XDH-AE-Q26-05-00029
A2: Cost Break Down
A3: SN | B3: Items/ Resources | C3: Remarks | D3: Unit Rate | E3: Count | F3: Months | G3: Price
A4: 1 | B4: Poject Manager | C4: Full Time | D4: 33000 | G4: =+SUM(D4*E4*F4) -> 0
A5: 2 | B5: Solution Architect | C5: Full Time | D5: 22000 | G5: =+SUM(D5*E5*F5) -> 0
A6: 3 | B6: AI Intergration Lead | C6: Full Time | D6: 19000 | G6: =+SUM(D6*E6*F6) -> 0
A7: 4 | B7: BIM/AWP Specialist | C7: Full Time | D7: 19000 | G7: =+SUM(D7*E7*F7) -> 0
A8: 5 | B8: Training Lead | C8: Full Time | D8: 22000 | G8: =+SUM(D8*E8*F8) -> 0
A9: 6 | B9: Document Controller | C9: Full Time | D9: 19000 | G9: =+SUM(D9*E9*F9) -> 0
A10: 8 | B10: Hardware + Licences | C10: 5% of resources | D10: 0.05 | G10: {=+SUM(G4:G8*D10)} -> 0
A11: 9 | B11: Margin | D11: 1 | G11: =+SUM(G4:G10)*D11 -> 0
A12: 10
A13: 11 | B13: Total (AED) | G13: ='Phase 1'!G14+'Phase 2'!G14+'Phase 3'!G14+'Phase 4'!G14 -> 2841125 | H13: =G13*2 -> 5682250
B14: VAT | G14: =G13*0.05 -> 142056.25 | H14: =G14*2 -> 284112.5
A15: 12 | B15: Total (AED) + VAT | G15: =+SUM(G13)* 1.05 -> 2983181.2 | H15: =G15*2 -> 5966362.5
A16: 13 | B16: Total (USD) | G16: =+SUM(G13)/3.65 -> 778390.41

Sheet Pricing Table
B1: 2026.06.01 XDH-AE-Q26-05-00029
A2: Cost Break Down
A3: SN | B3: Items/ Resources | C3: Remarks | D3: Count | E3: Months | F3: Price (AED) Excluding WHT | G3: Resources
A4: YEAR 1 - PHASE-BASED PRICING per SOW 3.3.10 (AI-Native delivery model)
A5: 1 | B5: Phase 1 | C5: Weeks 1-4: Requirement Finalization + Setup + Core Configuration. Human team: 2 FTE (PM + Solution Architect). AI agents handle ontology generation, RBAC config, integration scaffolding, doc generation. | D5: 1 | E5: 1 | F5: ='Phase 1'!G14 -> 232687.5 | G5: Project Manager Document Controller Solution Architect BIM/AWP Specialist
A6: 2 | B6: Phase 2 | C6: Weeks 5-12: Pilot Module Deployment on selected ARGP area. Human team: 3 FTE (SA + AI Lead + BIM Specialist). AI agents generate 80% of module config, integration code, dashboards, test cases. | D6: 1 | E6: 2 | F6: ='Phase 2'!G14 -> 625685 | G6: Project Manager Document Controller Solution Architect BIM/AWP Specialist AI Integration Specialist
A7: 3 | B7: Phase 3 | C7: Weeks 13-16: Pilot Validation + KPI Measurement + Training + Feedback. Human team: 2 FTE (SA + Training Lead). AI generates training content, KPI dashboards, feedback synthesis. | D7: 1 | E7: 1 | F7: ='Phase 3'!G14 -> 269832.5 | G7: Project Manager Document Controller Solution Architect BIM/AWP Specialist Training Lead
A8: 4 | B8: Phase 4 | C8: Weeks 17+: Full-Scale Rollout + M4 baseline + M5 dev + 1-mo hyper-care (no charge). Human team: 3 FTE avg ramping down. AI handles deployment automation, monitoring, Tier 1-2 support, change management. | D8: 1 | E8: 8 | F8: ='Phase 4'!G14 -> 1712920 | G8: Project Manager Document Controller Solution Architect BIM/AWP Specialist
B9: Sub-total Year 1 Phase Fees (One-time, AI-Native) | F9: =SUM(F5:F8) -> 2841125
E10: 5% WHT | F10: =F9*0.05 -> 142056.25
E11: Total Price | F11: =F9+F10 -> 2983181.2
A13: YEARS 2-5 RECURRING (5% p.a. escalation; lean run team 2-3 FTE AI-augmented)
A14: Year | B14: Description | C14: Price (AED) Excluding WHT
A15: Year 2 | B15: 15 %of the Build cost | C15: =F9*0.15 -> 426168.75
A16: Year 3 | B16: Year 2 x1.05 scalation | C16: =C15*1.05 -> 447477.19
A17: Year 4 | B17: Year 2 x1.10 scalation | C17: =C15*1.1 -> 468785.63
A18: Year 5 | B18: Year 2 x1.15 scalation | C18: =C15*1.15 -> 490094.06
B19: Total | C19: =F9+C15+C16+C17+C18 -> 4673650.6
C20: =C19*0.05 -> 233682.53 | D20: 5% WHT
C21: =C19+C20 -> 4907333.2 | D21: Total Price
A23: EXCLUSIONS - Maaden Direct Procurement (NOT in XDH price)
A24: 1 | B24: AI/LLM API subscriptions | C24: Claude+OpenAI+Gemini+embeddings | D24: Maaden enterprise agreement | F24: EXCLUDED
A25: 2 | B25: KSA in-Kingdom hosting | C25: STC Cloud / MS KSA / AWS Bahrain / NEOM / Mobily | D25: Maaden procures direct | F25: EXCLUDED
A26: 3 | B26: Compute / GPU infrastructure | C26: NVIDIA A100/H100 for CV + Digital Twin | D26: Maaden procures direct | F26: EXCLUDED
A27: 4 | B27: Object storage at scale | C27: Point clouds + imagery, PB-scale | D27: Maaden procures direct | F27: EXCLUDED
A28: 5 | B28: Vector database | C28: Pinecone / Weaviate enterprise tier | D28: Maaden procures direct | F28: EXCLUDED
A29: 6 | B29: Specialized SaaS | C29: Vision APIs / OCR / GIS | D29: Maaden procures direct | F29: EXCLUDED
A30: 7 | B30: Multi-affiliate tenants | C30: Beyond ARGP primary | D30: Variation per affiliate | F30: EXCLUDED
A31: 8 | B31: Annual compliance audits | C31: ISO 27001 / SOC 2 / pen test / PDPL | D31: Maaden procures direct | F31: EXCLUDED
A32: 9 | B32: Third-party software | C32: Primavera P6 / Revit / SAP / Aconex / Power BI / Aveva PI | D32: Maaden procures direct | F32: EXCLUDED
A33: 10 | B33: Hardware | C33: Laptops + IIoT sensors + RFID | D33: Maaden procures direct | F33: EXCLUDED

Sheet Rate for Variation
B1: On site Project team (Additional)
B2: SN | C2: Items/ Resources | D2: Remarks | E2: Price
B3: 1 | C3: BIM Manager | D3: Full Time (Onsite) | E3: 45,760
B4: 2 | C4: BIM Coordinator | D4: Full Time (Onsite) | E4: 34,320
B5: 3 | C5: BIM Modeler | D5: Full Time (Onsite) | E5: 26,400
B6: 4 | C6: Clash Detection Specialist | D6: Full Time (Onsite) | E6: 35,200
B8: Note: Onsite resource rates are not included within the original delivery scope or pricing structure. Any onsite presence requested during the project shall be considered a variation and charged separately in accordance with the above rates.
B9: Working Basis: 5 working days per week (~22 days per month), 8 hours per day.
B10: Price in AED
B13: Off-site Project team (For Variations or Extended Scope Use)
B14: SN | C14: Items/ Resources | D14: Remarks | E14: Monthly | F14: Daily | G14: Hourly
B15: 5 | C15: BIM Manager | D15: Full Time (Offsite) | E15: 42,240 | F15: 1,920 | G15: 240
B16: 6 | C16: BIM Coordinator | D16: Full Time (Offsite) | E16: 31,680 | F16: 1,440 | G16: 180
B17: 7 | C17: BIM Modeler | D17: Full Time (Offsite) | E17: 24,640 | F17: 1,120 | G17: 140
B18: 8 | C18: Clash Detection Specialist | D18: Full Time (Offsite) | E18: 33,440 | F18: 1,520 | G18: 190
B20: Note: The base proposal is structured on offsite delivery. Offsite rates shall be used as the baseline for any variations, additional scope, or extended duration.
B21: Working Basis: 5 working days per week (~22 days per month), 8 hours per day.
